django_ipay88/__init__.py
django_ipay88/models.py
django_ipay88/views.py
iPay88-0.0.3.dist-info/DESCRIPTION.rst
iPay88-0.0.3.dist-info/METADATA
iPay88-0.0.3.dist-info/metadata.json
iPay88-0.0.3.dist-info/RECORD
iPay88-0.0.3.dist-info/top_level.txt
iPay88-0.0.3.dist-info/WHEEL
