Metadata-Version: 2.0
Name: iPay88
Version: 0.0.3
Summary: iPay88 integration for Django
Home-page: https://bitbucket.org/mchauvinc/django-ipay88
Author: Mathieu Chauvinc
Author-email: mathieu@redapesolutions.com
License: MIT
Keywords: ipay88 payment gateway django
Platform: UNKNOWN
Classifier: Development Status :: 4 - Beta
Classifier: Intended Audience :: Developers
Classifier: Topic :: Software Development :: Build Tools
Classifier: License :: OSI Approved :: MIT License
Classifier: Programming Language :: Python :: 2
Classifier: Programming Language :: Python :: 2.6
Classifier: Programming Language :: Python :: 2.7
Classifier: Programming Language :: Python :: 3
Classifier: Programming Language :: Python :: 3.2
Classifier: Programming Language :: Python :: 3.3
Classifier: Programming Language :: Python :: 3.4
